traittypes/__init__.py
traittypes/_version.py
traittypes/traittypes.py
traittypes/utils.py
traittypes/tests/__init__.py
traittypes/tests/test_import_errors.py
traittypes/tests/test_traittypes.py
traittypes/tests/test_validators.py
traittypes-0.2.2.dist-info/licenses/LICENSE
traittypes-0.2.2.dist-info/METADATA
traittypes-0.2.2.dist-info/WHEEL
traittypes-0.2.2.dist-info/top_level.txt
traittypes-0.2.2.dist-info/RECORD
